README.md
setup.py
Idmeneo_cdQa.egg-info/PKG-INFO
Idmeneo_cdQa.egg-info/SOURCES.txt
Idmeneo_cdQa.egg-info/dependency_links.txt
Idmeneo_cdQa.egg-info/requires.txt
Idmeneo_cdQa.egg-info/top_level.txt
pipeline/__init__.py
pipeline/cdqa_sklearn.py
reader/__init__.py
reader/bertqa_sklearn.py
retriever/__init__.py
retriever/retriever_sklearn.py
retriever/text_transformers.py
retriever/vectorizers.py
utils/__init__.py
utils/converters.py
utils/download.py
utils/evaluation.py
utils/filters.py