Metadata-Version: 2.1
Name: Idmeneo-cdQa
Version: 0.0
Summary: An End-To-End Closed Domain Question Answering System with sciBert
Home-page: https://github.com/VincentVega002/Idomeneo_cdQa
Author: Gabor Jonas
License: Apache-2.0
Keywords: reading comprehension question answering deep learning natural language processing information retrieval bert
Platform: UNKNOWN
